{"pageContext":{"id":"cG9zdDoxMjU=","title":"Pos terefere kuku luku","uri":"/terefere/","excerpt":"<p>sadsadsadsadasdasdasdsa</p>\n","content":"\n<p>sadsadsadsadasdasdasdsa</p>\n","author":{"node":{"avatar":{"url":"https://secureservercdn.net/192.169.220.85/n4g.891.myftpupload.com/wp-content/uploads/2021/05/author@2.png?time=1621870334"},"name":"Alice Key"}},"categories":{"nodes":[{"name":"travel"}]},"date":"2021-05-21T16:54:16","featuredImage":{"node":{"srcSet":"https://n4g.891.myftpupload.com/wp-content/uploads/2021/05/dark-forest-300x200.jpg 300w, https://n4g.891.myftpupload.com/wp-content/uploads/2021/05/dark-forest-1024x683.jpg 1024w, https://n4g.891.myftpupload.com/wp-content/uploads/2021/05/dark-forest-768x512.jpg 768w, https://n4g.891.myftpupload.com/wp-content/uploads/2021/05/dark-forest.jpg 1280w","title":"dark-forest","sourceUrl":"https://secureservercdn.net/192.169.220.85/n4g.891.myftpupload.com/wp-content/uploads/2021/05/dark-forest.jpg?time=1621870334"}},"next":{"next":{"uri":"/travels/","title":"Travels"}}}}